lsbible/__init__.py
lsbible/books.py
lsbible/cache.py
lsbible/client.py
lsbible/exceptions.py
lsbible/models.py
lsbible/parser.py
lsbible/validators.py
lsbible/mcp/__init__.py
lsbible/mcp/server.py
lsbible-0.2.0.dist-info/METADATA
lsbible-0.2.0.dist-info/WHEEL
lsbible-0.2.0.dist-info/entry_points.txt
lsbible-0.2.0.dist-info/RECORD
