Metadata-Version: 2.4
Name: lsbible
Version: 0.2.0
Summary: LSBible API client - structured, type-safe Bible SDK
Project-URL: Homepage, https://github.com/kdcokenny/lsbible
Project-URL: Documentation, https://github.com/kdcokenny/lsbible/tree/main/packages/python-sdk
Project-URL: Repository, https://github.com/kdcokenny/lsbible
Project-URL: Issues, https://github.com/kdcokenny/lsbible/issues
Project-URL: Changelog, https://github.com/kdcokenny/lsbible/releases
Author-email: Kenny <lsbiblegh.g8d9w@passmail.net>
License: MIT
Keywords: api,bible,client,legacy-standard-bible,lsb,scripture,sdk
Classifier: Development Status :: 4 - Beta
Classifier: Intended Audience :: Developers
Classifier: License :: OSI Approved :: MIT License
Classifier: Programming Language :: Python :: 3
Classifier: Programming Language :: Python :: 3.12
Classifier: Programming Language :: Python :: 3.13
Classifier: Topic :: Religion
Classifier: Topic :: Software Development :: Libraries :: Python Modules
Classifier: Typing :: Typed
Requires-Python: >=3.12
Requires-Dist: beautifulsoup4>=4.12.0
Requires-Dist: httpx>=0.27.0
Requires-Dist: lxml>=5.0.0
Requires-Dist: pydantic>=2.0.0
Provides-Extra: server
Requires-Dist: fastmcp>=1.0.0; extra == 'server'
